linediff/__init__.py
linediff/__main__.py
linediff/diff.py
linediff/parser.py
linediff-0.1.3.dist-info/licenses/LICENSE
linediff-0.1.3.dist-info/METADATA
linediff-0.1.3.dist-info/WHEEL
linediff-0.1.3.dist-info/entry_points.txt
linediff-0.1.3.dist-info/top_level.txt
linediff-0.1.3.dist-info/RECORD
