Metadata-Version: 2.4
Name: linediff
Version: 0.1.3
Summary: A lightweight, syntax-aware diff tool for Python with tree-sitter integration
Author-email: Othmane BLIAL <blial.othmane@gmail.com>
Maintainer-email: Othmane BLIAL <blial.othmane@gmail.com>
License: MIT
Project-URL: Homepage, https://github.com/OthmaneBlial/linediff
Project-URL: Documentation, https://linediff.readthedocs.io/
Project-URL: Repository, https://github.com/OthmaneBlial/linediff.git
Project-URL: Issues, https://github.com/OthmaneBlial/linediff/issues
Project-URL: Changelog, https://github.com/OthmaneBlial/linediff/blob/main/CHANGELOG.md
Keywords: diff,syntax-aware,tree-sitter,git,comparison,structural-diff,code-analysis,development-tools
Classifier: Development Status :: 3 - Alpha
Classifier: Intended Audience :: Developers
Classifier: License :: OSI Approved :: MIT License
Classifier: Operating System :: OS Independent
Classifier: Programming Language :: Python :: 3
Classifier: Programming Language :: Python :: 3.8
Classifier: Programming Language :: Python :: 3.9
Classifier: Programming Language :: Python :: 3.10
Classifier: Programming Language :: Python :: 3.11
Classifier: Programming Language :: Python :: 3.12
Classifier: Topic :: Software Development :: Version Control :: Git
Classifier: Topic :: Text Processing :: General
Classifier: Topic :: Utilities
Requires-Python: >=3.8
License-File: LICENSE
Requires-Dist: typing-extensions>=4.0.0; python_version < "3.10"
Provides-Extra: tree-sitter
Requires-Dist: tree-sitter>=0.20.0; extra == "tree-sitter"
Requires-Dist: tree-sitter-python>=0.20.0; extra == "tree-sitter"
Requires-Dist: tree-sitter-javascript>=0.20.0; extra == "tree-sitter"
Requires-Dist: tree-sitter-json>=0.20.0; extra == "tree-sitter"
Requires-Dist: tree-sitter-html>=0.20.0; extra == "tree-sitter"
Requires-Dist: tree-sitter-css>=0.20.0; extra == "tree-sitter"
Requires-Dist: tree-sitter-rust>=0.20.0; extra == "tree-sitter"
Requires-Dist: tree-sitter-go>=0.20.0; extra == "tree-sitter"
Requires-Dist: tree-sitter-java>=0.20.0; extra == "tree-sitter"
Provides-Extra: dev
Requires-Dist: pytest>=7.0.0; extra == "dev"
Requires-Dist: pytest-cov>=4.0.0; extra == "dev"
Requires-Dist: black>=22.0.0; extra == "dev"
Requires-Dist: flake8>=4.0.0; extra == "dev"
Requires-Dist: mypy>=1.0.0; extra == "dev"
Requires-Dist: isort>=5.10.0; extra == "dev"
Requires-Dist: pre-commit>=2.20.0; extra == "dev"
Provides-Extra: docs
Requires-Dist: sphinx>=5.0.0; extra == "docs"
Requires-Dist: sphinx-rtd-theme>=1.0.0; extra == "docs"
Dynamic: license-file
